structy_generator/__init__.py
structy_generator/__main__.py
structy_generator/kinds.py
structy_generator/parser.py
structy_generator/templates/__init__.py
structy_generator/templates/c.header.jinja2
structy_generator/templates/c.source.jinja2
structy_generator/templates/js.jinja2
structy_generator/templates/py.jinja2
structy_generator-2021.2.3.dist-info/entry_points.txt
structy_generator-2021.2.3.dist-info/LICENSE
structy_generator-2021.2.3.dist-info/WHEEL
structy_generator-2021.2.3.dist-info/METADATA
structy_generator-2021.2.3.dist-info/RECORD
